aviary/envs/gsm8k/__init__.py
aviary/envs/gsm8k/env.py
aviary/envs/gsm8k/py.typed
aviary/envs/gsm8k/version.py
aviary_gsm8k-0.32.0.dist-info/METADATA
aviary_gsm8k-0.32.0.dist-info/WHEEL
aviary_gsm8k-0.32.0.dist-info/top_level.txt
aviary_gsm8k-0.32.0.dist-info/RECORD
