Metadata-Version: 2.4
Name: aviary.gsm8k
Version: 0.32.0
Summary: GSM8k environment implemented with aviary
Author-email: FutureHouse technical staff <hello@futurehouse.org>
Classifier: Intended Audience :: Developers
Classifier: License :: OSI Approved :: Apache Software License
Classifier: Operating System :: OS Independent
Classifier: Programming Language :: Python :: 3 :: Only
Classifier: Programming Language :: Python :: 3.11
Classifier: Programming Language :: Python :: 3.12
Classifier: Programming Language :: Python :: 3.13
Classifier: Programming Language :: Python :: 3.14
Classifier: Programming Language :: Python
Classifier: Topic :: Scientific/Engineering :: Artificial Intelligence
Requires-Python: >=3.11
Requires-Dist: datasets>=2.15
Requires-Dist: fhaviary
Requires-Dist: pydantic~=2.0
Provides-Extra: typing
Requires-Dist: pandas-stubs; extra == "typing"
